{"is_source_file": true, "format": "json", "description": ".json file: manifest.json", "external_files": [], "external_methods": [], "published": [], "classes": [], "methods": [], "calls": [], "search-terms": ["manifest.json", "json"], "state": 2, "file_id": 1, "knowledge_revision": 68, "git_revision": "950ec0a0d5ef1931431e02dbbf312d11fa0f572f", "revision_history": [{"15": "950ec0a0d5ef1931431e02dbbf312d11fa0f572f"}, {"68": "950ec0a0d5ef1931431e02dbbf312d11fa0f572f"}], "filename": "todo_frontend/public/manifest.json", "format-version": 4, "code-base-name": "https://github.com/kavia-common/simple-todo-list-223797-223814.git:kavia-main"}